{
  "keyword": "Titre accrocheur SEO",
  "intention": "informationnelle",
  "titre_h1": "Comment rédiger un titre SEO accrocheur : le guide pratique pour booster vos clics",
  "meta_description": "Découvrez comment créer un titre accrocheur SEO pour augmenter votre taux de clic. Guide complet avec des techniques, exemples concrets et erreurs à éviter.",
  "angle_editorial": "L'approche double-performance : optimiser pour les algorithmes de Google tout en utilisant des leviers psychologiques pour maximiser le taux de clic humain (CTR).",
  "query_fanout": [
    "Qu'est-ce qu'un titre SEO et pourquoi est-il fondamental pour le référencement ?",
    "Quelle est la différence cruciale entre une balise title et un titre H1 ?",
    "Comment un titre performant influence-t-il directement le taux de clic (CTR) et le ROI ?",
    "Quelles sont les méthodes et outils pour écrire un titre qui captive à la fois Google et les humains ?",
    "Quels sont des exemples concrets de titres qui génèrent des clics et pourquoi fonctionnent-ils ?"
  ],
  "structure": [
    {
      "h2": "Qu'est-ce qu'un titre SEO : définition et rôle stratégique",
      "points_cles": [
        "Définition de la balise <title> et son affichage (SERP, onglets, réseaux sociaux).",
        "Sa double fonction : signal de pertinence majeur pour les robots et principale incitation au clic pour les humains.",
        "Pourquoi le titre est le premier et le plus important point de contact entre votre contenu et l'utilisateur."
      ]
    },
    {
      "h2": "Balise title vs H1 : la distinction essentielle à maîtriser",
      "points_cles": [
        "La balise <title> : le titre 'externe' pour les moteurs de recherche, affiché hors de votre site.",
        "Le titre <h1> : le titre principal 'interne' de la page, structurant le contenu pour le lecteur.",
        "L'importance de la cohérence sémantique entre les deux tout en permettant une optimisation distincte."
      ]
    },
    {
      "h2": "L'impact mesurable : le lien direct entre titre, CTR et retour sur investissement",
      "points_cles": [
        "Explication du Taux de Clic (CTR) et pourquoi Google l'utilise comme un indicateur de pertinence.",
        "Démonstration : comment un titre optimisé augmente le trafic qualifié, même sans améliorer la position.",
        "Le titre comme levier de conversion gratuit et immédiat, agissant avant même la visite sur le site."
      ]
    },
    {
      "h2": "Méthode et outils pour rédiger le titre parfait",
      "points_cles": [
        "Placer le mot-clé cible principal au début pour un maximum d'impact SEO.",
        "Intégrer des déclencheurs psychologiques : chiffres, questions, nouveauté, bénéfices, urgence.",
        "Respecter la longueur optimale (~60 caractères / 580 pixels) pour éviter la troncature dans les SERP.",
        "Utiliser des outils de prévisualisation (SERP simulator) et d'analyse concurrentielle pour se différencier."
      ]
    },
    {
      "h2": "Analyse de 3 exemples concrets de titres efficaces",
      "points_cles": [
        "Décryptage d'un titre de type 'Liste' (ex: '10 astuces pour...') et son pouvoir psychologique.",
        "Analyse d'un titre de type 'Guide / Comment' qui répond parfaitement à l'intention de recherche.",
        "Étude d'un titre contenant une promesse forte ou un bénéfice clair pour l'utilisateur."
      ]
    }
  ],
  "mots_cles_secondaires": [
    "balise title",
    "optimisation titre",
    "meta titre",
    "taux de clic",
    "SERP",
    "référencement naturel",
    "CTR SEO"
  ],
  "questions_paa": [
    "Quelle est la longueur idéale d'un titre SEO ?",
    "Comment écrire un bon titre d'article ?",
    "C'est quoi un H1 en SEO ?"
  ],
  "ton": "pratique",
  "longueur_cible": 900,
  "category": "Contenu"
}